lkml2cube-0.2.10.dist-info/METADATA
lkml2cube-0.2.10.dist-info/WHEEL
lkml2cube-0.2.10.dist-info/entry_points.txt
lkml2cube-0.2.10.dist-info/licenses/LICENSE
lkml2cube/__init__.py
lkml2cube/converter.py
lkml2cube/main.py
lkml2cube/parser/__init__.py
lkml2cube/parser/cube_api.py
lkml2cube/parser/explores.py
lkml2cube/parser/loader.py
lkml2cube/parser/types.py
lkml2cube/parser/views.py
lkml2cube-0.2.10.dist-info/RECORD
