Metadata-Version: 2.1
Name: lkml2cube
Version: 0.2.10
Summary: Looker ML to Cube converter
Author-Email: Paco Valdez <paco@cube.dev>
License: MIT
Requires-Python: >=3.10
Requires-Dist: typer[all]>=0.9.0
Requires-Dist: lkml>=1.3.1
Requires-Dist: pyyaml>=6.0.1
Requires-Dist: rich>=13.7.1
Requires-Dist: requests>=2.32.4
Requires-Dist: pydoc-markdown>=4.8.2
